yieldfrom.py
yieldfrom-1.0.5.dist-info/LICENSE
yieldfrom-1.0.5.dist-info/METADATA
yieldfrom-1.0.5.dist-info/WHEEL
yieldfrom-1.0.5.dist-info/top_level.txt
yieldfrom-1.0.5.dist-info/RECORD
