Metadata-Version: 2.1
Name: yieldfrom
Version: 1.0.5
Summary: A backport of the `yield from` semantic from Python 3.x to Python 2.7
Home-page: https://github.com/Nurdok/yieldfrom/
Author: Amir Rachum
Author-email: amir@rachum.com
License: MIT
Keywords: yield,from,yield from,generators,backport,iterators
Platform: UNKNOWN
Classifier: Intended Audience :: Developers
Classifier: Environment :: Console
Classifier: Programming Language :: Python :: 2
Classifier: Programming Language :: Python :: 3
Classifier: Operating System :: OS Independent
Classifier: License :: OSI Approved :: MIT License
